fxutils/__init__.py
fxutils/historyreader/__init__.py
fxutils/historyreader/backtest_report.py
fxutils/historyreader/mql5.py
fxutils/historyreader/mt5.py
fxutils/historyreader/myfxbook.py
fxutils/historyreader/reader.py
fxutils/mt5wrapper.py
fxutils/portfolio/Portfolio.py
fxutils/portfolio/__init__.py
fxutils/tools/newsfilter.py
fxutils/utils.py
fxutils-0.1.0.dist-info/WHEEL
fxutils-0.1.0.dist-info/METADATA
fxutils-0.1.0.dist-info/RECORD
