Metadata-Version: 2.1
Name: fxutils
Version: 0.1.0
Summary: Forex utilities for automatic trading
Author: Xiaolei
Author-email: 26442779@qq.com
Requires-Python: >=3.9,<4.0
Classifier: Programming Language :: Python :: 3
Classifier: Programming Language :: Python :: 3.10
Classifier: Programming Language :: Python :: 3.9
Requires-Dist: MetaTrader5 (>=5.0.37,<6.0.0); sys_platform == "windows"
Requires-Dist: pandas (>=1.4.3,<2.0.0)
Requires-Dist: requests (>=2.28.1,<3.0.0)
